LICENSE.txt
MANIFEST.in
README.md
requirements.txt
setup.py
wechatautomation/__init__.py
wechatautomation/wxcore.py
wechatautomation/wxelements.py
wechatautomation/wxlogging.py
wechatautomation/wxutils.py
wechatautomation.egg-info/PKG-INFO
wechatautomation.egg-info/SOURCES.txt
wechatautomation.egg-info/dependency_links.txt
wechatautomation.egg-info/requires.txt
wechatautomation.egg-info/top_level.txt